{
  "@context": "http://iiif.io/api/presentation/3/context.json",
  "id": "https://markpbaggett.github.io/static_iiif/manifests/sample/cervantes-622.json",
  "type": "Manifest",
  "label": {
    "en": [
      "Engravings for Don Quixote"
    ]
  },
  "metadata": [
    {
      "label": {
        "en": [
          "year"
        ]
      },
      "value": {
        "en": [
          "c1750"
        ]
      }
    },
    {
      "label": {
        "en": [
          "place"
        ]
      },
      "value": {
        "en": [
          "Paris"
        ]
      }
    },
    {
      "label": {
        "en": [
          "publisher"
        ]
      },
      "value": {
        "en": [
          "Chez Radigues rue St. Jacque"
        ]
      }
    },
    {
      "label": {
        "en": [
          "author"
        ]
      },
      "value": {}
    },
    {
      "label": {
        "en": [
          "translator"
        ]
      },
      "value": {}
    },
    {
      "label": {
        "en": [
          "editor"
        ]
      },
      "value": {}
    },
    {
      "label": {
        "en": [
          "lang."
        ]
      },
      "value": {
        "en": [
          "FRE"
        ]
      }
    },
    {
      "label": {
        "en": [
          "vol."
        ]
      },
      "value": {
        "en": [
          "1"
        ]
      }
    },
    {
      "label": {
        "en": [
          "size"
        ]
      },
      "value": {
        "en": [
          "F"
        ]
      }
    },
    {
      "label": {
        "en": [
          "index"
        ]
      },
      "value": {
        "en": [
          "f. Albums and Engravings"
        ]
      }
    },
    {
      "label": {
        "en": [
          "references"
        ]
      },
      "value": {
        "en": [
          "A49"
        ]
      }
    },
    {
      "label": {
        "en": [
          "library"
        ]
      },
      "value": {
        "en": [
          "TAMU"
        ]
      }
    }
  ],
  "thumbnail": [
    {
      "id": "https://api-pre.library.tamu.edu/iiif/2/aHR0cHM6Ly9jZXJ2YW50ZXMubGlicmFyeS50YW11LmVkdS9jZXJ2YW50ZXMvRFFJSU1BR0VTL2luZGV4LzYyMi5naWY=/full/74,/0/default.jpg",
      "type": "Image",
      "height": 60,
      "width": 74,
      "service": [
        {
          "@id": "https://api-pre.library.tamu.edu/iiif/2/aHR0cHM6Ly9jZXJ2YW50ZXMubGlicmFyeS50YW11LmVkdS9jZXJ2YW50ZXMvRFFJSU1BR0VTL2luZGV4LzYyMi5naWY=",
          "@type": "ImageService2",
          "profile": "http://iiif.io/api/image/2/level2.json"
        }
      ],
      "format": "image/jpeg"
    }
  ],
  "items": []
}