{
  "@context": "http://iiif.io/api/presentation/3/context.json",
  "id": "https://markpbaggett.github.io/static_iiif/manifests/service_maps/20240813_0022.json",
  "type": "Manifest",
  "label": {
    "en": [
      "20240813_0022"
    ]
  },
  "metadata": [
    {
      "label": {
        "en": [
          "identifier"
        ]
      },
      "value": {
        "en": [
          "20240813_0022"
        ]
      }
    }
  ],
  "rights": "http://rightsstatements.org/vocab/NoC-US/1.0/",
  "items": [
    {
      "id": "https://markpbaggett.github.io/static_iiif/manifests/service_maps/bdb98c80-8a26-481c-a4ed-2b82a47335fa/canvas/1",
      "type": "Canvas",
      "label": {
        "en": [
          "Test"
        ]
      },
      "height": 6220,
      "width": 9239,
      "items": [
        {
          "id": "https://markpbaggett.github.io/static_iiif/manifests/service_maps/8b294687-2009-4014-962b-214c5f6461e1/canvas/1/canvas/1/annotation/1/page/1",
          "type": "AnnotationPage",
          "items": [
            {
              "id": "https://markpbaggett.github.io/static_iiif/manifests/service_maps/760c5e9e-a23a-4adc-940f-25c5cc9f0269/canvas/1/annotation/1",
              "type": "Annotation",
              "motivation": "painting",
              "body": {
                "id": "https://strob6zro3bzklrulaqu2545sy0odbvz.lambda-url.us-east-2.on.aws/iiif/3/2024-08-13/20240813_0022_1106th_Engineer_Combat_Group.jpg/full/max/0/default.jpg",
                "type": "Image",
                "height": 6220,
                "width": 9239,
                "service": [
                  {
                    "id": "https://strob6zro3bzklrulaqu2545sy0odbvz.lambda-url.us-east-2.on.aws/iiif/3/2024-08-13/20240813_0022_1106th_Engineer_Combat_Group.jpg",
                    "type": "ImageService3",
                    "profile": "level2"
                  }
                ],
                "format": "image/jpeg"
              },
              "target": "https://markpbaggett.github.io/static_iiif/manifests/service_maps/bdb98c80-8a26-481c-a4ed-2b82a47335fa/canvas/1"
            }
          ]
        }
      ]
    }
  ]
}