{
  "@context": "http://iiif.io/api/presentation/3/context.json",
  "id": "https://markpbaggett.github.io/static_iiif/manifests/service_maps/20240813_0005.json",
  "type": "Manifest",
  "label": {
    "en": [
      "20240813_0005"
    ]
  },
  "metadata": [
    {
      "label": {
        "en": [
          "identifier"
        ]
      },
      "value": {
        "en": [
          "20240813_0005"
        ]
      }
    }
  ],
  "rights": "http://rightsstatements.org/vocab/NoC-US/1.0/",
  "items": [
    {
      "id": "https://markpbaggett.github.io/static_iiif/manifests/service_maps/d830fedd-4735-4c89-ae6f-adfbc0179bc4/canvas/1",
      "type": "Canvas",
      "label": {
        "en": [
          "Test"
        ]
      },
      "height": 10060,
      "width": 14875,
      "thumbnail": [
        {
          "id": "https://strob6zro3bzklrulaqu2545sy0odbvz.lambda-url.us-east-2.on.aws/iiif/3/2024-08-13/20240813_0005_97_Inf_Div_ETO.jpg/full/232,157/0/default.jpg",
          "type": "Image",
          "height": 157,
          "width": 232,
          "service": [
            {
              "id": "https://strob6zro3bzklrulaqu2545sy0odbvz.lambda-url.us-east-2.on.aws/iiif/3/2024-08-13/20240813_0005_97_Inf_Div_ETO.jpg",
              "type": "ImageService3",
              "profile": "level2"
            }
          ],
          "format": "image/jpeg"
        }
      ],
      "items": [
        {
          "id": "https://markpbaggett.github.io/static_iiif/manifests/service_maps/37f6c70a-6e9e-4869-b230-bc0aa411322a/canvas/1/canvas/1/annotation/1/page/1",
          "type": "AnnotationPage",
          "items": [
            {
              "id": "https://markpbaggett.github.io/static_iiif/manifests/service_maps/b596f8a1-1055-4c84-8ec7-163cd7061065/canvas/1/annotation/1",
              "type": "Annotation",
              "motivation": "painting",
              "body": {
                "id": "https://strob6zro3bzklrulaqu2545sy0odbvz.lambda-url.us-east-2.on.aws/iiif/3/2024-08-13/20240813_0005_97_Inf_Div_ETO.jpg/full/max/0/default.jpg",
                "type": "Image",
                "height": 10060,
                "width": 14875,
                "service": [
                  {
                    "id": "https://strob6zro3bzklrulaqu2545sy0odbvz.lambda-url.us-east-2.on.aws/iiif/3/2024-08-13/20240813_0005_97_Inf_Div_ETO.jpg",
                    "type": "ImageService3",
                    "profile": "level2"
                  }
                ],
                "format": "image/jpeg"
              },
              "target": "https://markpbaggett.github.io/static_iiif/manifests/service_maps/d830fedd-4735-4c89-ae6f-adfbc0179bc4/canvas/1"
            }
          ]
        }
      ]
    }
  ]
}