{
  "@context": "http://iiif.io/api/presentation/3/context.json",
  "id": "https://markpbaggett.github.io/static_iiif/manifests/service_maps/20240813_0008.json",
  "type": "Manifest",
  "label": {
    "en": [
      "20240813_0008"
    ]
  },
  "metadata": [
    {
      "label": {
        "en": [
          "identifier"
        ]
      },
      "value": {
        "en": [
          "20240813_0008"
        ]
      }
    }
  ],
  "rights": "http://rightsstatements.org/vocab/NoC-US/1.0/",
  "items": [
    {
      "id": "https://markpbaggett.github.io/static_iiif/manifests/service_maps/0d4dd54e-48ec-406e-a76c-e153642cba48/canvas/1",
      "type": "Canvas",
      "label": {
        "en": [
          "Test"
        ]
      },
      "height": 9299,
      "width": 11947,
      "items": [
        {
          "id": "https://markpbaggett.github.io/static_iiif/manifests/service_maps/39211615-bbdc-4a5d-bdc4-3eade6fe0bd7/canvas/1/canvas/1/annotation/1/page/1",
          "type": "AnnotationPage",
          "items": [
            {
              "id": "https://markpbaggett.github.io/static_iiif/manifests/service_maps/04dfd1b3-c58e-489f-9e41-61a4e19312ac/canvas/1/annotation/1",
              "type": "Annotation",
              "motivation": "painting",
              "body": {
                "id": "https://strob6zro3bzklrulaqu2545sy0odbvz.lambda-url.us-east-2.on.aws/iiif/3/2024-08-13/20240813_0008_70th_Tank_Battalion.jpg/full/max/0/default.jpg",
                "type": "Image",
                "height": 9299,
                "width": 11947,
                "service": [
                  {
                    "id": "https://strob6zro3bzklrulaqu2545sy0odbvz.lambda-url.us-east-2.on.aws/iiif/3/2024-08-13/20240813_0008_70th_Tank_Battalion.jpg",
                    "type": "ImageService3",
                    "profile": "level2"
                  }
                ],
                "format": "image/jpeg"
              },
              "target": "https://markpbaggett.github.io/static_iiif/manifests/service_maps/0d4dd54e-48ec-406e-a76c-e153642cba48/canvas/1"
            }
          ]
        }
      ]
    }
  ]
}