{
  "@context": [
    "http://iiif.io/api/extension/navplace/context.json",
    "http://iiif.io/api/presentation/3/context.json"
  ],
  "id": "https://aboltion-now-manifests.s3.us-east-2.amazonaws.com/0123_nohateinmyholler.json",
  "type": "Manifest",
  "label": {
    "en": [
      "No Hate in My Holler"
    ]
  },
  "metadata": [
    {
      "label": {
        "en": [
          "Artist"
        ]
      },
      "value": {
        "en": [
          "Lacy Hale"
        ]
      }
    }
  ],
  "rights": "http://rightsstatements.org/vocab/InC/1.0/",
  "homepage": [
    {
      "id": "https://abolition-now.github.io/an/works/no-hate-in-my-holler",
      "type": "Text",
      "label": {
        "en": [
          "No Hate in My Holler"
        ]
      },
      "format": "text/html",
      "language": [
        "en"
      ]
    }
  ],
  "items": [
    {
      "id": "https://aboltion-now-manifests.s3.us-east-2.amazonaws.com/0123_nohateinmyholler_oo.jpg/canvas/1",
      "type": "Canvas",
      "label": {
        "en": [
          "Original Image"
        ]
      },
      "height": 1124,
      "width": 1536,
      "metadata": [
        {
          "label": {
            "en": [
              "Missing metadata?"
            ]
          },
          "value": {
            "en": [
              "Yes"
            ]
          }
        }
      ],
      "thumbnail": [
        {
          "id": "https://strob6zro3bzklrulaqu2545sy0odbvz.lambda-url.us-east-2.on.aws/iiif/3/0123_nohateinmyholler_oo.jpg/full/384,281/0/default.jpg",
          "type": "Image",
          "height": 281,
          "width": 384,
          "service": [
            {
              "id": "https://strob6zro3bzklrulaqu2545sy0odbvz.lambda-url.us-east-2.on.aws/iiif/3/0123_nohateinmyholler_oo.jpg",
              "type": "ImageService3",
              "profile": "level2"
            }
          ],
          "format": "image/jpeg"
        }
      ],
      "items": [
        {
          "id": "https://aboltion-now-manifests.s3.us-east-2.amazonaws.com/0123_nohateinmyholler_oo.jpg/canvas/1/annotation/1/page/1",
          "type": "AnnotationPage",
          "items": [
            {
              "id": "https://aboltion-now-manifests.s3.us-east-2.amazonaws.com/0123_nohateinmyholler_oo.jpg/canvas/1/annotation/1",
              "type": "Annotation",
              "motivation": "painting",
              "body": {
                "id": "https://strob6zro3bzklrulaqu2545sy0odbvz.lambda-url.us-east-2.on.aws/iiif/3/0123_nohateinmyholler_oo.jpg/full/max/0/default.jpg",
                "type": "Image",
                "height": 1124,
                "width": 1536,
                "service": [
                  {
                    "id": "https://strob6zro3bzklrulaqu2545sy0odbvz.lambda-url.us-east-2.on.aws/iiif/3/0123_nohateinmyholler_oo.jpg",
                    "type": "ImageService3",
                    "profile": "level2"
                  }
                ],
                "format": "image/jpeg"
              },
              "target": "https://aboltion-now-manifests.s3.us-east-2.amazonaws.com/0123_nohateinmyholler_oo.jpg/canvas/1"
            }
          ]
        }
      ]
    },
    {
      "id": "https://aboltion-now-manifests.s3.us-east-2.amazonaws.com/0123_nohateinmyholler_oo1.jpg/canvas/2",
      "type": "Canvas",
      "label": {
        "en": [
          "Original Image"
        ]
      },
      "height": 1124,
      "width": 1536,
      "metadata": [
        {
          "label": {
            "en": [
              "Missing metadata?"
            ]
          },
          "value": {
            "en": [
              "Yes"
            ]
          }
        }
      ],
      "thumbnail": [
        {
          "id": "https://strob6zro3bzklrulaqu2545sy0odbvz.lambda-url.us-east-2.on.aws/iiif/3/0123_nohateinmyholler_oo1.jpg/full/384,281/0/default.jpg",
          "type": "Image",
          "height": 281,
          "width": 384,
          "service": [
            {
              "id": "https://strob6zro3bzklrulaqu2545sy0odbvz.lambda-url.us-east-2.on.aws/iiif/3/0123_nohateinmyholler_oo1.jpg",
              "type": "ImageService3",
              "profile": "level2"
            }
          ],
          "format": "image/jpeg"
        }
      ],
      "items": [
        {
          "id": "https://aboltion-now-manifests.s3.us-east-2.amazonaws.com/0123_nohateinmyholler_oo1.jpg/canvas/2/annotation/1/page/1",
          "type": "AnnotationPage",
          "items": [
            {
              "id": "https://aboltion-now-manifests.s3.us-east-2.amazonaws.com/0123_nohateinmyholler_oo1.jpg/canvas/2/annotation/1",
              "type": "Annotation",
              "motivation": "painting",
              "body": {
                "id": "https://strob6zro3bzklrulaqu2545sy0odbvz.lambda-url.us-east-2.on.aws/iiif/3/0123_nohateinmyholler_oo1.jpg/full/max/0/default.jpg",
                "type": "Image",
                "height": 1124,
                "width": 1536,
                "service": [
                  {
                    "id": "https://strob6zro3bzklrulaqu2545sy0odbvz.lambda-url.us-east-2.on.aws/iiif/3/0123_nohateinmyholler_oo1.jpg",
                    "type": "ImageService3",
                    "profile": "level2"
                  }
                ],
                "format": "image/jpeg"
              },
              "target": "https://aboltion-now-manifests.s3.us-east-2.amazonaws.com/0123_nohateinmyholler_oo1.jpg/canvas/2"
            }
          ]
        }
      ]
    },
    {
      "id": "https://aboltion-now-manifests.s3.us-east-2.amazonaws.com/0123_nohateinmyholler_ru.png/canvas/3",
      "type": "Canvas",
      "label": {
        "en": [
          "Reuse"
        ]
      },
      "height": 1194,
      "width": 2200,
      "metadata": [
        {
          "label": {
            "en": [
              "Missing metadata?"
            ]
          },
          "value": {
            "en": [
              "Yes"
            ]
          }
        }
      ],
      "thumbnail": [
        {
          "id": "https://strob6zro3bzklrulaqu2545sy0odbvz.lambda-url.us-east-2.on.aws/iiif/3/0123_nohateinmyholler_ru.png/full/550,298/0/default.jpg",
          "type": "Image",
          "height": 298,
          "width": 550,
          "service": [
            {
              "id": "https://strob6zro3bzklrulaqu2545sy0odbvz.lambda-url.us-east-2.on.aws/iiif/3/0123_nohateinmyholler_ru.png",
              "type": "ImageService3",
              "profile": "level2"
            }
          ],
          "format": "image/jpeg"
        }
      ],
      "items": [
        {
          "id": "https://aboltion-now-manifests.s3.us-east-2.amazonaws.com/0123_nohateinmyholler_ru.png/canvas/3/annotation/1/page/1",
          "type": "AnnotationPage",
          "items": [
            {
              "id": "https://aboltion-now-manifests.s3.us-east-2.amazonaws.com/0123_nohateinmyholler_ru.png/canvas/3/annotation/1",
              "type": "Annotation",
              "motivation": "painting",
              "body": {
                "id": "https://strob6zro3bzklrulaqu2545sy0odbvz.lambda-url.us-east-2.on.aws/iiif/3/0123_nohateinmyholler_ru.png/full/max/0/default.jpg",
                "type": "Image",
                "height": 1194,
                "width": 2200,
                "service": [
                  {
                    "id": "https://strob6zro3bzklrulaqu2545sy0odbvz.lambda-url.us-east-2.on.aws/iiif/3/0123_nohateinmyholler_ru.png",
                    "type": "ImageService3",
                    "profile": "level2"
                  }
                ],
                "format": "image/jpeg"
              },
              "target": "https://aboltion-now-manifests.s3.us-east-2.amazonaws.com/0123_nohateinmyholler_ru.png/canvas/3"
            }
          ]
        }
      ]
    },
    {
      "id": "https://aboltion-now-manifests.s3.us-east-2.amazonaws.com/0123_nohateinmyholler_ru1.png/canvas/4",
      "type": "Canvas",
      "label": {
        "en": [
          "Reuse"
        ]
      },
      "height": 1438,
      "width": 1984,
      "metadata": [
        {
          "label": {
            "en": [
              "Missing metadata?"
            ]
          },
          "value": {
            "en": [
              "Yes"
            ]
          }
        }
      ],
      "thumbnail": [
        {
          "id": "https://strob6zro3bzklrulaqu2545sy0odbvz.lambda-url.us-east-2.on.aws/iiif/3/0123_nohateinmyholler_ru1.png/full/496,359/0/default.jpg",
          "type": "Image",
          "height": 359,
          "width": 496,
          "service": [
            {
              "id": "https://strob6zro3bzklrulaqu2545sy0odbvz.lambda-url.us-east-2.on.aws/iiif/3/0123_nohateinmyholler_ru1.png",
              "type": "ImageService3",
              "profile": "level2"
            }
          ],
          "format": "image/jpeg"
        }
      ],
      "items": [
        {
          "id": "https://aboltion-now-manifests.s3.us-east-2.amazonaws.com/0123_nohateinmyholler_ru1.png/canvas/4/annotation/1/page/1",
          "type": "AnnotationPage",
          "items": [
            {
              "id": "https://aboltion-now-manifests.s3.us-east-2.amazonaws.com/0123_nohateinmyholler_ru1.png/canvas/4/annotation/1",
              "type": "Annotation",
              "motivation": "painting",
              "body": {
                "id": "https://strob6zro3bzklrulaqu2545sy0odbvz.lambda-url.us-east-2.on.aws/iiif/3/0123_nohateinmyholler_ru1.png/full/max/0/default.jpg",
                "type": "Image",
                "height": 1438,
                "width": 1984,
                "service": [
                  {
                    "id": "https://strob6zro3bzklrulaqu2545sy0odbvz.lambda-url.us-east-2.on.aws/iiif/3/0123_nohateinmyholler_ru1.png",
                    "type": "ImageService3",
                    "profile": "level2"
                  }
                ],
                "format": "image/jpeg"
              },
              "target": "https://aboltion-now-manifests.s3.us-east-2.amazonaws.com/0123_nohateinmyholler_ru1.png/canvas/4"
            }
          ]
        }
      ]
    },
    {
      "id": "https://aboltion-now-manifests.s3.us-east-2.amazonaws.com/0123_nohateinmyholler_ru10.png/canvas/5",
      "type": "Canvas",
      "label": {
        "en": [
          "Reuse"
        ]
      },
      "height": 1166,
      "width": 1784,
      "metadata": [
        {
          "label": {
            "en": [
              "Missing metadata?"
            ]
          },
          "value": {
            "en": [
              "Yes"
            ]
          }
        }
      ],
      "thumbnail": [
        {
          "id": "https://strob6zro3bzklrulaqu2545sy0odbvz.lambda-url.us-east-2.on.aws/iiif/3/0123_nohateinmyholler_ru10.png/full/446,291/0/default.jpg",
          "type": "Image",
          "height": 291,
          "width": 446,
          "service": [
            {
              "id": "https://strob6zro3bzklrulaqu2545sy0odbvz.lambda-url.us-east-2.on.aws/iiif/3/0123_nohateinmyholler_ru10.png",
              "type": "ImageService3",
              "profile": "level2"
            }
          ],
          "format": "image/jpeg"
        }
      ],
      "items": [
        {
          "id": "https://aboltion-now-manifests.s3.us-east-2.amazonaws.com/0123_nohateinmyholler_ru10.png/canvas/5/annotation/1/page/1",
          "type": "AnnotationPage",
          "items": [
            {
              "id": "https://aboltion-now-manifests.s3.us-east-2.amazonaws.com/0123_nohateinmyholler_ru10.png/canvas/5/annotation/1",
              "type": "Annotation",
              "motivation": "painting",
              "body": {
                "id": "https://strob6zro3bzklrulaqu2545sy0odbvz.lambda-url.us-east-2.on.aws/iiif/3/0123_nohateinmyholler_ru10.png/full/max/0/default.jpg",
                "type": "Image",
                "height": 1166,
                "width": 1784,
                "service": [
                  {
                    "id": "https://strob6zro3bzklrulaqu2545sy0odbvz.lambda-url.us-east-2.on.aws/iiif/3/0123_nohateinmyholler_ru10.png",
                    "type": "ImageService3",
                    "profile": "level2"
                  }
                ],
                "format": "image/jpeg"
              },
              "target": "https://aboltion-now-manifests.s3.us-east-2.amazonaws.com/0123_nohateinmyholler_ru10.png/canvas/5"
            }
          ]
        }
      ]
    },
    {
      "id": "https://aboltion-now-manifests.s3.us-east-2.amazonaws.com/0123_nohateinmyholler_ru2.jpg/canvas/6",
      "type": "Canvas",
      "label": {
        "en": [
          "Reuse"
        ]
      },
      "height": 1000,
      "width": 1000,
      "metadata": [
        {
          "label": {
            "en": [
              "Missing metadata?"
            ]
          },
          "value": {
            "en": [
              "Yes"
            ]
          }
        }
      ],
      "thumbnail": [
        {
          "id": "https://strob6zro3bzklrulaqu2545sy0odbvz.lambda-url.us-east-2.on.aws/iiif/3/0123_nohateinmyholler_ru2.jpg/full/500,500/0/default.jpg",
          "type": "Image",
          "height": 500,
          "width": 500,
          "service": [
            {
              "id": "https://strob6zro3bzklrulaqu2545sy0odbvz.lambda-url.us-east-2.on.aws/iiif/3/0123_nohateinmyholler_ru2.jpg",
              "type": "ImageService3",
              "profile": "level2"
            }
          ],
          "format": "image/jpeg"
        }
      ],
      "items": [
        {
          "id": "https://aboltion-now-manifests.s3.us-east-2.amazonaws.com/0123_nohateinmyholler_ru2.jpg/canvas/6/annotation/1/page/1",
          "type": "AnnotationPage",
          "items": [
            {
              "id": "https://aboltion-now-manifests.s3.us-east-2.amazonaws.com/0123_nohateinmyholler_ru2.jpg/canvas/6/annotation/1",
              "type": "Annotation",
              "motivation": "painting",
              "body": {
                "id": "https://strob6zro3bzklrulaqu2545sy0odbvz.lambda-url.us-east-2.on.aws/iiif/3/0123_nohateinmyholler_ru2.jpg/full/max/0/default.jpg",
                "type": "Image",
                "height": 1000,
                "width": 1000,
                "service": [
                  {
                    "id": "https://strob6zro3bzklrulaqu2545sy0odbvz.lambda-url.us-east-2.on.aws/iiif/3/0123_nohateinmyholler_ru2.jpg",
                    "type": "ImageService3",
                    "profile": "level2"
                  }
                ],
                "format": "image/jpeg"
              },
              "target": "https://aboltion-now-manifests.s3.us-east-2.amazonaws.com/0123_nohateinmyholler_ru2.jpg/canvas/6"
            }
          ]
        }
      ]
    },
    {
      "id": "https://aboltion-now-manifests.s3.us-east-2.amazonaws.com/0123_nohateinmyholler_ru3.png/canvas/7",
      "type": "Canvas",
      "label": {
        "en": [
          "Reuse"
        ]
      },
      "height": 1196,
      "width": 2198,
      "metadata": [
        {
          "label": {
            "en": [
              "Missing metadata?"
            ]
          },
          "value": {
            "en": [
              "Yes"
            ]
          }
        }
      ],
      "thumbnail": [
        {
          "id": "https://strob6zro3bzklrulaqu2545sy0odbvz.lambda-url.us-east-2.on.aws/iiif/3/0123_nohateinmyholler_ru3.png/full/549,299/0/default.jpg",
          "type": "Image",
          "height": 299,
          "width": 549,
          "service": [
            {
              "id": "https://strob6zro3bzklrulaqu2545sy0odbvz.lambda-url.us-east-2.on.aws/iiif/3/0123_nohateinmyholler_ru3.png",
              "type": "ImageService3",
              "profile": "level2"
            }
          ],
          "format": "image/jpeg"
        }
      ],
      "items": [
        {
          "id": "https://aboltion-now-manifests.s3.us-east-2.amazonaws.com/0123_nohateinmyholler_ru3.png/canvas/7/annotation/1/page/1",
          "type": "AnnotationPage",
          "items": [
            {
              "id": "https://aboltion-now-manifests.s3.us-east-2.amazonaws.com/0123_nohateinmyholler_ru3.png/canvas/7/annotation/1",
              "type": "Annotation",
              "motivation": "painting",
              "body": {
                "id": "https://strob6zro3bzklrulaqu2545sy0odbvz.lambda-url.us-east-2.on.aws/iiif/3/0123_nohateinmyholler_ru3.png/full/max/0/default.jpg",
                "type": "Image",
                "height": 1196,
                "width": 2198,
                "service": [
                  {
                    "id": "https://strob6zro3bzklrulaqu2545sy0odbvz.lambda-url.us-east-2.on.aws/iiif/3/0123_nohateinmyholler_ru3.png",
                    "type": "ImageService3",
                    "profile": "level2"
                  }
                ],
                "format": "image/jpeg"
              },
              "target": "https://aboltion-now-manifests.s3.us-east-2.amazonaws.com/0123_nohateinmyholler_ru3.png/canvas/7"
            }
          ]
        }
      ]
    },
    {
      "id": "https://aboltion-now-manifests.s3.us-east-2.amazonaws.com/0123_nohateinmyholler_ru5.png/canvas/8",
      "type": "Canvas",
      "label": {
        "en": [
          "Reuse"
        ]
      },
      "height": 1486,
      "width": 2196,
      "metadata": [
        {
          "label": {
            "en": [
              "Missing metadata?"
            ]
          },
          "value": {
            "en": [
              "Yes"
            ]
          }
        }
      ],
      "thumbnail": [
        {
          "id": "https://strob6zro3bzklrulaqu2545sy0odbvz.lambda-url.us-east-2.on.aws/iiif/3/0123_nohateinmyholler_ru5.png/full/549,371/0/default.jpg",
          "type": "Image",
          "height": 371,
          "width": 549,
          "service": [
            {
              "id": "https://strob6zro3bzklrulaqu2545sy0odbvz.lambda-url.us-east-2.on.aws/iiif/3/0123_nohateinmyholler_ru5.png",
              "type": "ImageService3",
              "profile": "level2"
            }
          ],
          "format": "image/jpeg"
        }
      ],
      "items": [
        {
          "id": "https://aboltion-now-manifests.s3.us-east-2.amazonaws.com/0123_nohateinmyholler_ru5.png/canvas/8/annotation/1/page/1",
          "type": "AnnotationPage",
          "items": [
            {
              "id": "https://aboltion-now-manifests.s3.us-east-2.amazonaws.com/0123_nohateinmyholler_ru5.png/canvas/8/annotation/1",
              "type": "Annotation",
              "motivation": "painting",
              "body": {
                "id": "https://strob6zro3bzklrulaqu2545sy0odbvz.lambda-url.us-east-2.on.aws/iiif/3/0123_nohateinmyholler_ru5.png/full/max/0/default.jpg",
                "type": "Image",
                "height": 1486,
                "width": 2196,
                "service": [
                  {
                    "id": "https://strob6zro3bzklrulaqu2545sy0odbvz.lambda-url.us-east-2.on.aws/iiif/3/0123_nohateinmyholler_ru5.png",
                    "type": "ImageService3",
                    "profile": "level2"
                  }
                ],
                "format": "image/jpeg"
              },
              "target": "https://aboltion-now-manifests.s3.us-east-2.amazonaws.com/0123_nohateinmyholler_ru5.png/canvas/8"
            }
          ]
        }
      ]
    },
    {
      "id": "https://aboltion-now-manifests.s3.us-east-2.amazonaws.com/0123_nohateinmyholler_ru6.jpg/canvas/9",
      "type": "Canvas",
      "label": {
        "en": [
          "Reuse"
        ]
      },
      "height": 1294,
      "width": 1440,
      "metadata": [
        {
          "label": {
            "en": [
              "Missing metadata?"
            ]
          },
          "value": {
            "en": [
              "Yes"
            ]
          }
        }
      ],
      "thumbnail": [
        {
          "id": "https://strob6zro3bzklrulaqu2545sy0odbvz.lambda-url.us-east-2.on.aws/iiif/3/0123_nohateinmyholler_ru6.jpg/full/360,323/0/default.jpg",
          "type": "Image",
          "height": 323,
          "width": 360,
          "service": [
            {
              "id": "https://strob6zro3bzklrulaqu2545sy0odbvz.lambda-url.us-east-2.on.aws/iiif/3/0123_nohateinmyholler_ru6.jpg",
              "type": "ImageService3",
              "profile": "level2"
            }
          ],
          "format": "image/jpeg"
        }
      ],
      "items": [
        {
          "id": "https://aboltion-now-manifests.s3.us-east-2.amazonaws.com/0123_nohateinmyholler_ru6.jpg/canvas/9/annotation/1/page/1",
          "type": "AnnotationPage",
          "items": [
            {
              "id": "https://aboltion-now-manifests.s3.us-east-2.amazonaws.com/0123_nohateinmyholler_ru6.jpg/canvas/9/annotation/1",
              "type": "Annotation",
              "motivation": "painting",
              "body": {
                "id": "https://strob6zro3bzklrulaqu2545sy0odbvz.lambda-url.us-east-2.on.aws/iiif/3/0123_nohateinmyholler_ru6.jpg/full/max/0/default.jpg",
                "type": "Image",
                "height": 1294,
                "width": 1440,
                "service": [
                  {
                    "id": "https://strob6zro3bzklrulaqu2545sy0odbvz.lambda-url.us-east-2.on.aws/iiif/3/0123_nohateinmyholler_ru6.jpg",
                    "type": "ImageService3",
                    "profile": "level2"
                  }
                ],
                "format": "image/jpeg"
              },
              "target": "https://aboltion-now-manifests.s3.us-east-2.amazonaws.com/0123_nohateinmyholler_ru6.jpg/canvas/9"
            }
          ]
        }
      ]
    },
    {
      "id": "https://aboltion-now-manifests.s3.us-east-2.amazonaws.com/0123_nohateinmyholler_ru7.jpg/canvas/10",
      "type": "Canvas",
      "label": {
        "en": [
          "Reuse"
        ]
      },
      "height": 872,
      "width": 872,
      "metadata": [
        {
          "label": {
            "en": [
              "Missing metadata?"
            ]
          },
          "value": {
            "en": [
              "Yes"
            ]
          }
        }
      ],
      "thumbnail": [
        {
          "id": "https://strob6zro3bzklrulaqu2545sy0odbvz.lambda-url.us-east-2.on.aws/iiif/3/0123_nohateinmyholler_ru7.jpg/full/436,436/0/default.jpg",
          "type": "Image",
          "height": 436,
          "width": 436,
          "service": [
            {
              "id": "https://strob6zro3bzklrulaqu2545sy0odbvz.lambda-url.us-east-2.on.aws/iiif/3/0123_nohateinmyholler_ru7.jpg",
              "type": "ImageService3",
              "profile": "level2"
            }
          ],
          "format": "image/jpeg"
        }
      ],
      "items": [
        {
          "id": "https://aboltion-now-manifests.s3.us-east-2.amazonaws.com/0123_nohateinmyholler_ru7.jpg/canvas/10/annotation/1/page/1",
          "type": "AnnotationPage",
          "items": [
            {
              "id": "https://aboltion-now-manifests.s3.us-east-2.amazonaws.com/0123_nohateinmyholler_ru7.jpg/canvas/10/annotation/1",
              "type": "Annotation",
              "motivation": "painting",
              "body": {
                "id": "https://strob6zro3bzklrulaqu2545sy0odbvz.lambda-url.us-east-2.on.aws/iiif/3/0123_nohateinmyholler_ru7.jpg/full/max/0/default.jpg",
                "type": "Image",
                "height": 872,
                "width": 872,
                "service": [
                  {
                    "id": "https://strob6zro3bzklrulaqu2545sy0odbvz.lambda-url.us-east-2.on.aws/iiif/3/0123_nohateinmyholler_ru7.jpg",
                    "type": "ImageService3",
                    "profile": "level2"
                  }
                ],
                "format": "image/jpeg"
              },
              "target": "https://aboltion-now-manifests.s3.us-east-2.amazonaws.com/0123_nohateinmyholler_ru7.jpg/canvas/10"
            }
          ]
        }
      ]
    },
    {
      "id": "https://aboltion-now-manifests.s3.us-east-2.amazonaws.com/0123_nohateinmyholler_ru8.png/canvas/11",
      "type": "Canvas",
      "label": {
        "en": [
          "Reuse"
        ]
      },
      "height": 1204,
      "width": 2218,
      "metadata": [
        {
          "label": {
            "en": [
              "Missing metadata?"
            ]
          },
          "value": {
            "en": [
              "Yes"
            ]
          }
        }
      ],
      "thumbnail": [
        {
          "id": "https://strob6zro3bzklrulaqu2545sy0odbvz.lambda-url.us-east-2.on.aws/iiif/3/0123_nohateinmyholler_ru8.png/full/554,301/0/default.jpg",
          "type": "Image",
          "height": 301,
          "width": 554,
          "service": [
            {
              "id": "https://strob6zro3bzklrulaqu2545sy0odbvz.lambda-url.us-east-2.on.aws/iiif/3/0123_nohateinmyholler_ru8.png",
              "type": "ImageService3",
              "profile": "level2"
            }
          ],
          "format": "image/jpeg"
        }
      ],
      "items": [
        {
          "id": "https://aboltion-now-manifests.s3.us-east-2.amazonaws.com/0123_nohateinmyholler_ru8.png/canvas/11/annotation/1/page/1",
          "type": "AnnotationPage",
          "items": [
            {
              "id": "https://aboltion-now-manifests.s3.us-east-2.amazonaws.com/0123_nohateinmyholler_ru8.png/canvas/11/annotation/1",
              "type": "Annotation",
              "motivation": "painting",
              "body": {
                "id": "https://strob6zro3bzklrulaqu2545sy0odbvz.lambda-url.us-east-2.on.aws/iiif/3/0123_nohateinmyholler_ru8.png/full/max/0/default.jpg",
                "type": "Image",
                "height": 1204,
                "width": 2218,
                "service": [
                  {
                    "id": "https://strob6zro3bzklrulaqu2545sy0odbvz.lambda-url.us-east-2.on.aws/iiif/3/0123_nohateinmyholler_ru8.png",
                    "type": "ImageService3",
                    "profile": "level2"
                  }
                ],
                "format": "image/jpeg"
              },
              "target": "https://aboltion-now-manifests.s3.us-east-2.amazonaws.com/0123_nohateinmyholler_ru8.png/canvas/11"
            }
          ]
        }
      ]
    },
    {
      "id": "https://aboltion-now-manifests.s3.us-east-2.amazonaws.com/0123_nohateinmyholler_ru9.png/canvas/12",
      "type": "Canvas",
      "label": {
        "en": [
          "Reuse"
        ]
      },
      "height": 1200,
      "width": 1778,
      "metadata": [
        {
          "label": {
            "en": [
              "Missing metadata?"
            ]
          },
          "value": {
            "en": [
              "Yes"
            ]
          }
        }
      ],
      "thumbnail": [
        {
          "id": "https://strob6zro3bzklrulaqu2545sy0odbvz.lambda-url.us-east-2.on.aws/iiif/3/0123_nohateinmyholler_ru9.png/full/444,300/0/default.jpg",
          "type": "Image",
          "height": 300,
          "width": 444,
          "service": [
            {
              "id": "https://strob6zro3bzklrulaqu2545sy0odbvz.lambda-url.us-east-2.on.aws/iiif/3/0123_nohateinmyholler_ru9.png",
              "type": "ImageService3",
              "profile": "level2"
            }
          ],
          "format": "image/jpeg"
        }
      ],
      "items": [
        {
          "id": "https://aboltion-now-manifests.s3.us-east-2.amazonaws.com/0123_nohateinmyholler_ru9.png/canvas/12/annotation/1/page/1",
          "type": "AnnotationPage",
          "items": [
            {
              "id": "https://aboltion-now-manifests.s3.us-east-2.amazonaws.com/0123_nohateinmyholler_ru9.png/canvas/12/annotation/1",
              "type": "Annotation",
              "motivation": "painting",
              "body": {
                "id": "https://strob6zro3bzklrulaqu2545sy0odbvz.lambda-url.us-east-2.on.aws/iiif/3/0123_nohateinmyholler_ru9.png/full/max/0/default.jpg",
                "type": "Image",
                "height": 1200,
                "width": 1778,
                "service": [
                  {
                    "id": "https://strob6zro3bzklrulaqu2545sy0odbvz.lambda-url.us-east-2.on.aws/iiif/3/0123_nohateinmyholler_ru9.png",
                    "type": "ImageService3",
                    "profile": "level2"
                  }
                ],
                "format": "image/jpeg"
              },
              "target": "https://aboltion-now-manifests.s3.us-east-2.amazonaws.com/0123_nohateinmyholler_ru9.png/canvas/12"
            }
          ]
        }
      ]
    }
  ]
}