{
  "@context": [
    "http://iiif.io/api/extension/navplace/context.json",
    "http://iiif.io/api/presentation/3/context.json"
  ],
  "id": "https://aboltion-now-manifests.s3.us-east-2.amazonaws.com/0253_batjpodswebinar.json",
  "type": "Manifest",
  "label": {
    "en": [
      "Pods 101 "
    ]
  },
  "metadata": [
    {
      "label": {
        "en": [
          "Subject"
        ]
      },
      "value": {
        "en": [
          "Transformative Justice",
          "Restorative Justice"
        ]
      }
    },
    {
      "label": {
        "en": [
          "Artist"
        ]
      },
      "value": {
        "en": [
          "Tracy Nguyen, hellafly.graphics"
        ]
      }
    }
  ],
  "rights": "http://rightsstatements.org/vocab/InC/1.0/",
  "homepage": [
    {
      "id": "https://abolition-now.github.io/an/works/pods-101",
      "type": "Text",
      "label": {
        "en": [
          "Pods 101 "
        ]
      },
      "format": "text/html",
      "language": [
        "en"
      ]
    }
  ],
  "items": [
    {
      "id": "https://aboltion-now-manifests.s3.us-east-2.amazonaws.com/0253_batjpodswebinar_oo.jpeg/canvas/1",
      "type": "Canvas",
      "label": {
        "en": [
          "Original Image"
        ]
      },
      "height": 1078,
      "width": 1440,
      "metadata": [
        {
          "label": {
            "en": [
              "Subject"
            ]
          },
          "value": {
            "en": [
              "Transformative Justice",
              "Restorative Justice"
            ]
          }
        }
      ],
      "thumbnail": [
        {
          "id": "https://strob6zro3bzklrulaqu2545sy0odbvz.lambda-url.us-east-2.on.aws/iiif/3/0253_batjpodswebinar_oo.jpeg/full/360,269/0/default.jpg",
          "type": "Image",
          "height": 269,
          "width": 360,
          "service": [
            {
              "id": "https://strob6zro3bzklrulaqu2545sy0odbvz.lambda-url.us-east-2.on.aws/iiif/3/0253_batjpodswebinar_oo.jpeg",
              "type": "ImageService3",
              "profile": "level2"
            }
          ],
          "format": "image/jpeg"
        }
      ],
      "items": [
        {
          "id": "https://aboltion-now-manifests.s3.us-east-2.amazonaws.com/0253_batjpodswebinar_oo.jpeg/canvas/1/annotation/1/page/1",
          "type": "AnnotationPage",
          "items": [
            {
              "id": "https://aboltion-now-manifests.s3.us-east-2.amazonaws.com/0253_batjpodswebinar_oo.jpeg/canvas/1/annotation/1",
              "type": "Annotation",
              "motivation": "painting",
              "body": {
                "id": "https://strob6zro3bzklrulaqu2545sy0odbvz.lambda-url.us-east-2.on.aws/iiif/3/0253_batjpodswebinar_oo.jpeg/full/max/0/default.jpg",
                "type": "Image",
                "height": 1078,
                "width": 1440,
                "service": [
                  {
                    "id": "https://strob6zro3bzklrulaqu2545sy0odbvz.lambda-url.us-east-2.on.aws/iiif/3/0253_batjpodswebinar_oo.jpeg",
                    "type": "ImageService3",
                    "profile": "level2"
                  }
                ],
                "format": "image/jpeg"
              },
              "target": "https://aboltion-now-manifests.s3.us-east-2.amazonaws.com/0253_batjpodswebinar_oo.jpeg/canvas/1"
            }
          ]
        }
      ]
    },
    {
      "id": "https://aboltion-now-manifests.s3.us-east-2.amazonaws.com/0253_batjpodswebinar_oo1.jpeg/canvas/2",
      "type": "Canvas",
      "label": {
        "en": [
          "Original Image"
        ]
      },
      "height": 630,
      "width": 842,
      "metadata": [
        {
          "label": {
            "en": [
              "Subject"
            ]
          },
          "value": {
            "en": [
              "Transformative Justice"
            ]
          }
        }
      ],
      "thumbnail": [
        {
          "id": "https://strob6zro3bzklrulaqu2545sy0odbvz.lambda-url.us-east-2.on.aws/iiif/3/0253_batjpodswebinar_oo1.jpeg/full/421,315/0/default.jpg",
          "type": "Image",
          "height": 315,
          "width": 421,
          "service": [
            {
              "id": "https://strob6zro3bzklrulaqu2545sy0odbvz.lambda-url.us-east-2.on.aws/iiif/3/0253_batjpodswebinar_oo1.jpeg",
              "type": "ImageService3",
              "profile": "level2"
            }
          ],
          "format": "image/jpeg"
        }
      ],
      "items": [
        {
          "id": "https://aboltion-now-manifests.s3.us-east-2.amazonaws.com/0253_batjpodswebinar_oo1.jpeg/canvas/2/annotation/1/page/1",
          "type": "AnnotationPage",
          "items": [
            {
              "id": "https://aboltion-now-manifests.s3.us-east-2.amazonaws.com/0253_batjpodswebinar_oo1.jpeg/canvas/2/annotation/1",
              "type": "Annotation",
              "motivation": "painting",
              "body": {
                "id": "https://strob6zro3bzklrulaqu2545sy0odbvz.lambda-url.us-east-2.on.aws/iiif/3/0253_batjpodswebinar_oo1.jpeg/full/max/0/default.jpg",
                "type": "Image",
                "height": 630,
                "width": 842,
                "service": [
                  {
                    "id": "https://strob6zro3bzklrulaqu2545sy0odbvz.lambda-url.us-east-2.on.aws/iiif/3/0253_batjpodswebinar_oo1.jpeg",
                    "type": "ImageService3",
                    "profile": "level2"
                  }
                ],
                "format": "image/jpeg"
              },
              "target": "https://aboltion-now-manifests.s3.us-east-2.amazonaws.com/0253_batjpodswebinar_oo1.jpeg/canvas/2"
            }
          ]
        }
      ]
    },
    {
      "id": "https://aboltion-now-manifests.s3.us-east-2.amazonaws.com/0253_batjpodswebinar_oo2.jpeg/canvas/3",
      "type": "Canvas",
      "label": {
        "en": [
          "Original Image"
        ]
      },
      "height": 631,
      "width": 842,
      "metadata": [
        {
          "label": {
            "en": [
              "Subject"
            ]
          },
          "value": {
            "en": [
              "Transformative Justice",
              "Restorative Justice"
            ]
          }
        }
      ],
      "thumbnail": [
        {
          "id": "https://strob6zro3bzklrulaqu2545sy0odbvz.lambda-url.us-east-2.on.aws/iiif/3/0253_batjpodswebinar_oo2.jpeg/full/421,315/0/default.jpg",
          "type": "Image",
          "height": 315,
          "width": 421,
          "service": [
            {
              "id": "https://strob6zro3bzklrulaqu2545sy0odbvz.lambda-url.us-east-2.on.aws/iiif/3/0253_batjpodswebinar_oo2.jpeg",
              "type": "ImageService3",
              "profile": "level2"
            }
          ],
          "format": "image/jpeg"
        }
      ],
      "items": [
        {
          "id": "https://aboltion-now-manifests.s3.us-east-2.amazonaws.com/0253_batjpodswebinar_oo2.jpeg/canvas/3/annotation/1/page/1",
          "type": "AnnotationPage",
          "items": [
            {
              "id": "https://aboltion-now-manifests.s3.us-east-2.amazonaws.com/0253_batjpodswebinar_oo2.jpeg/canvas/3/annotation/1",
              "type": "Annotation",
              "motivation": "painting",
              "body": {
                "id": "https://strob6zro3bzklrulaqu2545sy0odbvz.lambda-url.us-east-2.on.aws/iiif/3/0253_batjpodswebinar_oo2.jpeg/full/max/0/default.jpg",
                "type": "Image",
                "height": 631,
                "width": 842,
                "service": [
                  {
                    "id": "https://strob6zro3bzklrulaqu2545sy0odbvz.lambda-url.us-east-2.on.aws/iiif/3/0253_batjpodswebinar_oo2.jpeg",
                    "type": "ImageService3",
                    "profile": "level2"
                  }
                ],
                "format": "image/jpeg"
              },
              "target": "https://aboltion-now-manifests.s3.us-east-2.amazonaws.com/0253_batjpodswebinar_oo2.jpeg/canvas/3"
            }
          ]
        }
      ]
    }
  ]
}