{
  "@context": [
    "http://iiif.io/api/extension/navplace/context.json",
    "http://iiif.io/api/presentation/3/context.json"
  ],
  "id": "https://aboltion-now-manifests.s3.us-east-2.amazonaws.com/0260_stopcopcity.json",
  "type": "Manifest",
  "label": {
    "en": [
      "This is not just a policing issue"
    ]
  },
  "metadata": [
    {
      "label": {
        "en": [
          "Slogans"
        ]
      },
      "value": {
        "en": [
          "Stop Cop City"
        ]
      }
    },
    {
      "label": {
        "en": [
          "Visual Motifs"
        ]
      },
      "value": {
        "en": [
          "Pigs"
        ]
      }
    },
    {
      "label": {
        "en": [
          "Subject"
        ]
      },
      "value": {
        "en": [
          "Housing Justice",
          "Militarization",
          "Police"
        ]
      }
    },
    {
      "label": {
        "en": [
          "Geography"
        ]
      },
      "value": {
        "en": [
          "Atlanta, GA, USA"
        ]
      }
    },
    {
      "label": {
        "en": [
          "Artist"
        ]
      },
      "value": {
        "en": [
          "Strike MoMA"
        ]
      }
    }
  ],
  "rights": "http://rightsstatements.org/vocab/InC/1.0/",
  "navPlace": {
    "type": "FeatureCollection",
    "features": [
      {
        "id": "https://aboltion-now-manifests.s3.us-east-2.amazonaws.com/notdereferenceable/feature/0",
        "type": "Feature",
        "properties": {
          "label": {
            "en": [
              "This is not just a policing issue -- Atlanta, GA, USA"
            ]
          }
        },
        "geometry": {
          "type": "Point",
          "coordinates": [
            -84.39079285320364,
            33.74903599710342
          ]
        }
      }
    ]
  },
  "homepage": [
    {
      "id": "https://abolition-now.github.io/an/works/this-is-not-just-a-policing-issue",
      "type": "Text",
      "label": {
        "en": [
          "This is not just a policing issue"
        ]
      },
      "format": "text/html",
      "language": [
        "en"
      ]
    }
  ],
  "items": [
    {
      "id": "https://aboltion-now-manifests.s3.us-east-2.amazonaws.com/0260_stopcopcity_oo.jpeg/canvas/1",
      "type": "Canvas",
      "label": {
        "en": [
          "Original Image"
        ]
      },
      "height": 1787,
      "width": 1440,
      "metadata": [
        {
          "label": {
            "en": [
              "Slogans"
            ]
          },
          "value": {
            "en": [
              "Stop Cop City"
            ]
          }
        },
        {
          "label": {
            "en": [
              "Visual Motifs"
            ]
          },
          "value": {
            "en": [
              "Pigs"
            ]
          }
        },
        {
          "label": {
            "en": [
              "Subject"
            ]
          },
          "value": {
            "en": [
              "Housing Justice",
              "Militarization",
              "Police"
            ]
          }
        },
        {
          "label": {
            "en": [
              "Geography"
            ]
          },
          "value": {
            "en": [
              "Atlanta, GA, USA"
            ]
          }
        }
      ],
      "thumbnail": [
        {
          "id": "https://strob6zro3bzklrulaqu2545sy0odbvz.lambda-url.us-east-2.on.aws/iiif/3/0260_stopcopcity_oo.jpeg/full/360,446/0/default.jpg",
          "type": "Image",
          "height": 446,
          "width": 360,
          "service": [
            {
              "id": "https://strob6zro3bzklrulaqu2545sy0odbvz.lambda-url.us-east-2.on.aws/iiif/3/0260_stopcopcity_oo.jpeg",
              "type": "ImageService3",
              "profile": "level2"
            }
          ],
          "format": "image/jpeg"
        }
      ],
      "items": [
        {
          "id": "https://aboltion-now-manifests.s3.us-east-2.amazonaws.com/0260_stopcopcity_oo.jpeg/canvas/1/annotation/1/page/1",
          "type": "AnnotationPage",
          "items": [
            {
              "id": "https://aboltion-now-manifests.s3.us-east-2.amazonaws.com/0260_stopcopcity_oo.jpeg/canvas/1/annotation/1",
              "type": "Annotation",
              "motivation": "painting",
              "body": {
                "id": "https://strob6zro3bzklrulaqu2545sy0odbvz.lambda-url.us-east-2.on.aws/iiif/3/0260_stopcopcity_oo.jpeg/full/max/0/default.jpg",
                "type": "Image",
                "height": 1787,
                "width": 1440,
                "service": [
                  {
                    "id": "https://strob6zro3bzklrulaqu2545sy0odbvz.lambda-url.us-east-2.on.aws/iiif/3/0260_stopcopcity_oo.jpeg",
                    "type": "ImageService3",
                    "profile": "level2"
                  }
                ],
                "format": "image/jpeg"
              },
              "target": "https://aboltion-now-manifests.s3.us-east-2.amazonaws.com/0260_stopcopcity_oo.jpeg/canvas/1"
            }
          ]
        }
      ]
    }
  ]
}